MANIFEST.in
README.rst
geocode_csv
setup.py
giokoda/__init__.py
giokoda/settings.py
giokoda/utils.py
giokoda.egg-info/PKG-INFO
giokoda.egg-info/PKG-INFO~
giokoda.egg-info/SOURCES.txt
giokoda.egg-info/dependency_links.txt
giokoda.egg-info/requires.txt
giokoda.egg-info/top_level.txt