Metadata-Version: 1.1
Name: giokoda
Version: 0.1.1
Summary: A utility for geocoding csv files.
Home-page: https://pypi.python.org/pypi/giokoda
Author: Emil
Author-email: emil@tehamalab.com
License: Apache License, Version 2.0
Download-URL: https://github.com/WorldBank-Transport/giokoda/tarball/0.1.1
Platform: UNKNOWN
Classifier: Intended Audience :: Developers
Classifier: Intended Audience :: Science/Research
Classifier: Operating System :: OS Independent
Classifier: Programming Language :: Python
Classifier: License :: OSI Approved :: Apache Software License
Classifier: Topic :: Scientific/Engineering :: GIS
Classifier: Topic :: Software Development :: Libraries :: Python Modules
Classifier: Programming Language :: Python :: 2
Classifier: Programming Language :: Python :: 2.7
Classifier: Programming Language :: Python :: 3
Classifier: Programming Language :: Python :: 3.2
Classifier: Programming Language :: Python :: 3.3
Classifier: Programming Language :: Python :: 3.4
Classifier: Programming Language :: Python :: Implementation :: CPython
Classifier: Programming Language :: Python :: Implementation :: PyPy
